youtubesdk/__init__.py
youtubesdk/base.py
youtubesdk/constants.py
youtubesdk/exceptions.py
youtube_sdk_py-0.1.0.dist-info/LICENSE
youtube_sdk_py-0.1.0.dist-info/METADATA
youtube_sdk_py-0.1.0.dist-info/WHEEL
youtube_sdk_py-0.1.0.dist-info/top_level.txt
youtube_sdk_py-0.1.0.dist-info/RECORD
