Metadata-Version: 2.1
Name: youtube-sdk-py
Version: 0.1.0
Summary: Python SDK for accessing Youtube APIs
Home-page: https://github.com/polydimensional/youtube-sdk-py
Author: Ashwin Thanaraj
Author-email: ashwinthanaraj@gmail.com
License: MIT
Keywords: youtube,api,python,sdk,pip
Platform: UNKNOWN
Classifier: Topic :: Internet :: WWW/HTTP
Classifier: Intended Audience :: Developers
Classifier: Programming Language :: Python :: 3
Classifier: License :: OSI Approved :: MIT License
Classifier: Operating System :: OS Independent
Requires-Dist: requests
